rebapy/__init__.py
rebapy/client.py
rebapy/stripped_tx.py
rebapy-0.0.1.dist-info/METADATA
rebapy-0.0.1.dist-info/WHEEL
rebapy-0.0.1.dist-info/licenses/LICENSE
rebapy-0.0.1.dist-info/RECORD
