Metadata-Version: 2.1
Name: rebapy
Version: 0.0.1
Summary: Reba Python Client
Project-URL: Homepage, https://github.com/multisig-labs/rebapy
Project-URL: Bug Tracker, https://github.com/multisig-labs/rebapy/issues
Author-email: Chandler Lofland <chandler@usereba.com>
License-File: LICENSE
Classifier: Operating System :: OS Independent
Classifier: Programming Language :: Python :: 3
Requires-Python: >=3.9
Requires-Dist: web3>=5.31.0
